vereshchaginpy/__init__.py
vereshchaginpy/vereshchagin_core.py
vereshchaginpy/vereshchagin_figures.py
vereshchaginpy/vereshchagin_pairs.py
vereshchaginpy/vereshchagin_visualise.py
vereshchaginpy-0.1.4.dist-info/licenses/LICENSE
vereshchaginpy-0.1.4.dist-info/METADATA
vereshchaginpy-0.1.4.dist-info/WHEEL
vereshchaginpy-0.1.4.dist-info/top_level.txt
vereshchaginpy-0.1.4.dist-info/RECORD
