Metadata-Version: 2.4
Name: vereshchaginpy
Version: 0.1.4
Summary: Graph-based integration for structural mechanics using the Vereshchagin method
Home-page: https://github.com/Haudkozaur/VereshchaginPy
Author: Julian Haudek
Author-email: julianhaudek@gmail.com
Classifier: Programming Language :: Python :: 3
Classifier: License :: OSI Approved :: MIT License
Classifier: Operating System :: OS Independent
Requires-Python: >=3.7
License-File: LICENSE
Requires-Dist: matplotlib
Requires-Dist: numpy
Dynamic: author
Dynamic: author-email
Dynamic: classifier
Dynamic: description
Dynamic: description-content-type
Dynamic: home-page
Dynamic: license-file
Dynamic: requires-dist
Dynamic: requires-python
Dynamic: summary
